fluvio-0.21.0.dist-info/RECORD
fluvio-0.21.0.dist-info/WHEEL
fluvio-0.21.0.dist-info/top_level.txt
fluvio-0.21.0.dist-info/METADATA
fluvio-0.21.0.dist-info/licenses/LICENSE-APACHE
fluvio/specs.py
fluvio/cloud.py
fluvio/__init__.py
fluvio/utils.py
fluvio/_fluvio_python.cpython-311-darwin.so
fluvio/topic.py
fluvio/record.py
