Metadata-Version: 2.4
Name: fluvio
Version: 0.21.0
Summary: Python client library for Fluvio
Author-email: Fluvio Contributors <team@fluvio.io>
License-Expression: Apache-2.0
Project-URL: Bug Reports, https://github.com/infinyon/fluvio-client-python/issues
Project-URL: Source, https://github.com/infinyon/fluvio-client-python
Keywords: fluvio,streaming,stream
Classifier: Intended Audience :: Developers
Classifier: Programming Language :: Python :: 3
Classifier: Programming Language :: Python :: 3.9
Classifier: Programming Language :: Python :: 3.10
Classifier: Programming Language :: Python :: 3.11
Classifier: Programming Language :: Python :: 3.12
Classifier: Programming Language :: Python :: 3.13
Classifier: Programming Language :: Python :: 3 :: Only
Requires-Python: >=3.9
License-File: LICENSE-APACHE
Requires-Dist: msgpack==1.0.4
Requires-Dist: semantic-version==2.10.0
Requires-Dist: humanfriendly==10.0
Provides-Extra: dev
Requires-Dist: flake8==7.1.1; extra == "dev"
Requires-Dist: mccabe==0.7.0; extra == "dev"
Requires-Dist: pycodestyle==2.12.1; extra == "dev"
Requires-Dist: pyflakes==3.2.0; extra == "dev"
Requires-Dist: black==25.1.0; extra == "dev"
Requires-Dist: setuptools-rust==1.11.1; extra == "dev"
Requires-Dist: toml==0.10.2; extra == "dev"
Requires-Dist: build==1.2.2.post1; extra == "dev"
Requires-Dist: pytest>=8; extra == "dev"
Requires-Dist: cibuildwheel>=2.22; extra == "dev"
Dynamic: license-file
